{
	"name": "pipeline1",
	"properties": {
		"activities": [
			{
				"name": "LookupCurrentChangeTrackingVersionActivity",
				"type": "Lookup",
				"dependsOn": [],
				"policy": {
					"timeout": "0.12:00:00",
					"retry": 0,
					"retryIntervalInSeconds": 30,
					"secureOutput": false,
					"secureInput": false
				},
				"userProperties": [],
				"typeProperties": {
					"source": {
						"type": "AzureSqlSource",
						"sqlReaderQuery": "SELECT CHANGE_TRACKING_CURRENT_VERSION() as CurrentChangeTrackingVersion",
						"queryTimeout": "02:00:00",
						"partitionOption": "None"
					},
					"dataset": {
						"referenceName": "ds_customer_venu",
						"type": "DatasetReference"
					},
					"firstRowOnly": false
				}
			},
			{
				"name": "LookupLastChangeTrackingVersionActivity",
				"type": "Lookup",
				"dependsOn": [],
				"policy": {
					"timeout": "0.12:00:00",
					"retry": 0,
					"retryIntervalInSeconds": 30,
					"secureOutput": false,
					"secureInput": false
				},
				"userProperties": [],
				"typeProperties": {
					"source": {
						"type": "AzureSqlSource",
						"queryTimeout": "02:00:00",
						"partitionOption": "None"
					},
					"dataset": {
						"referenceName": "ds_cvt_venu",
						"type": "DatasetReference"
					},
					"firstRowOnly": false
				}
			},
			{
				"name": "Copy data1",
				"type": "Copy",
				"dependsOn": [
					{
						"activity": "LookupLastChangeTrackingVersionActivity",
						"dependencyConditions": [
							"Succeeded"
						]
					},
					{
						"activity": "LookupCurrentChangeTrackingVersionActivity",
						"dependencyConditions": [
							"Succeeded"
						]
					}
				],
				"policy": {
					"timeout": "0.12:00:00",
					"retry": 0,
					"retryIntervalInSeconds": 30,
					"secureOutput": false,
					"secureInput": false
				},
				"userProperties": [],
				"typeProperties": {
					"source": {
						"type": "AzureSqlSource",
						"sqlReaderQuery": {
							"value": "SELECT \n\tcustomer_venu.CustomerID,\n\tcustomer_venu.CustomerName,\n\tcustomer_venu.ContactNumber,\n\tcustomer_venu.Address, \n\tCT.SYS_CHANGE_VERSION, \n\tSYS_CHANGE_OPERATION \nfrom customer_venu\n\tRIGHT OUTER JOIN \n\tCHANGETABLE(\n\t\tCHANGES customer_venu, \n\t\t@{activity('LookupLastChangeTrackingVersionActivity').output.value[0].SYS_CHANGE_VERSION}\n\t\t) AS CT \n\tON \n\tcustomer_venu.CustomerID = CT.CustomerID\n\twhere \n\t\tCT.SYS_CHANGE_VERSION <= @{activity('LookupCurrentChangeTrackingVersionActivity').output.value[0].CurrentChangeTrackingVersion}\n",
							"type": "Expression"
						},
						"queryTimeout": "02:00:00",
						"partitionOption": "None"
					},
					"sink": {
						"type": "DelimitedTextSink",
						"storeSettings": {
							"type": "AzureBlobFSWriteSettings"
						},
						"formatSettings": {
							"type": "DelimitedTextWriteSettings",
							"quoteAllText": true,
							"fileExtension": ".txt"
						}
					},
					"enableStaging": false,
					"translator": {
						"type": "TabularTranslator",
						"typeConversion": true,
						"typeConversionSettings": {
							"allowDataTruncation": true,
							"treatBooleanAsNumber": false
						}
					}
				},
				"inputs": [
					{
						"referenceName": "ds_customer_venu",
						"type": "DatasetReference"
					}
				],
				"outputs": [
					{
						"referenceName": "ds_gen2_venu",
						"type": "DatasetReference"
					}
				]
			},
			{
				"name": "Stored procedure1",
				"type": "SqlServerStoredProcedure",
				"dependsOn": [
					{
						"activity": "Copy data1",
						"dependencyConditions": [
							"Succeeded"
						]
					}
				],
				"policy": {
					"timeout": "0.12:00:00",
					"retry": 0,
					"retryIntervalInSeconds": 30,
					"secureOutput": false,
					"secureInput": false
				},
				"userProperties": [],
				"typeProperties": {
					"storedProcedureName": "[dbo].[venu_Update_ChangeTracking_Version]",
					"storedProcedureParameters": {
						"CurrentTrackingVersion": {
							"value": {
								"value": "@{activity('LookupCurrentChangeTrackingVersionActivity').output.value[0].CurrentChangeTrackingVersion}",
								"type": "Expression"
							},
							"type": "Int64"
						},
						"TableName": {
							"value": {
								"value": "@{activity('LookupLastChangeTrackingVersionActivity').output.value[0].TableName}",
								"type": "Expression"
							},
							"type": "String"
						}
					}
				},
				"linkedServiceName": {
					"referenceName": "LS_SQL_VENU",
					"type": "LinkedServiceReference"
				}
			}
		],
		"annotations": []
	}
}